apimate/__init__.py
apimate/api.py
apimate/arq.py
apimate/exceptions.py
apimate/http.py
apimate/memory.py
apimate/query.py
apimate/types.py
apimate/mongodb/__init__.py
apimate/mongodb/crud.py
apimate/mongodb/query.py
apimate/mongodb/repo.py
apimate/mongodb/types.py
tests/mongodb/__init__.py
tests/mongodb/conftest.py
tests/mongodb/test_crud.py
tests/mongodb/test_multirepo.py
tests/mongodb/test_query.py
tests/mongodb/test_repo.py
tests/mongodb/test_types.py
apimate-0.1.4.dist-info/METADATA
apimate-0.1.4.dist-info/WHEEL
apimate-0.1.4.dist-info/top_level.txt
apimate-0.1.4.dist-info/RECORD
